{
    "name": "Tavro\\Bundle\\ApiBundle\\Handler\\FileHandler",
    "line": 19,
    "short_desc": "Class FileHandler",
    "long_desc": "",
    "hint": null,
    "tags": {
        "package": [
            [
                "Tavro\\Bundle\\ApiBundle\\Handler"
            ]
        ]
    },
    "namespace": "Tavro\\Bundle\\ApiBundle\\Handler",
    "file": "..\/api\/src\/Tavro\/Bundle\/ApiBundle\/Handler\/FileHandler.php",
    "relative_file": null,
    "hash": "d0ae26d8024294e6d6bc9518fb63797be3eb32a4",
    "parent": "Tavro\\Bundle\\ApiBundle\\Services\\EntityHandler",
    "modifiers": "Stmt_Class",
    "is_trait": false,
    "is_interface": false,
    "aliases": {
        "EntityInterface": "Tavro\\Bundle\\CoreBundle\\Model\\EntityInterface",
        "EntityHandler": "Tavro\\Bundle\\ApiBundle\\Services\\EntityHandler",
        "ApiException": "Tavro\\Bundle\\ApiBundle\\Exception\\ApiException",
        "ApiAccessDeniedException": "Tavro\\Bundle\\ApiBundle\\Exception\\ApiAccessDeniedException",
        "User": "Tavro\\Bundle\\CoreBundle\\Entity\\User",
        "Mod": "Tavro\\Bundle\\CoreBundle\\Entity\\Mod",
        "ModFile": "Tavro\\Bundle\\CoreBundle\\Entity\\ModFile",
        "UploadedFile": "Symfony\\Component\\HttpFoundation\\File\\UploadedFile"
    },
    "errors": [],
    "interfaces": [],
    "traits": [],
    "properties": [],
    "methods": {
        "getBucket": {
            "name": "getBucket",
            "line": 24,
            "short_desc": "",
            "long_desc": "",
            "hint": [
                [
                    "mixed",
                    false
                ]
            ],
            "hint_desc": "",
            "tags": [],
            "modifiers": "1",
            "is_by_ref": "",
            "exceptions": [],
            "errors": [],
            "parameters": []
        },
        "getAdapter": {
            "name": "getAdapter",
            "line": 37,
            "short_desc": "Based on the directory, build the adapter file system.",
            "long_desc": "",
            "hint": [
                [
                    "mixed",
                    false
                ]
            ],
            "hint_desc": "",
            "tags": [],
            "modifiers": "1",
            "is_by_ref": "",
            "exceptions": [
                [
                    "\\Exception",
                    ""
                ]
            ],
            "errors": [],
            "parameters": {
                "directory": {
                    "name": "directory",
                    "line": 37,
                    "short_desc": "",
                    "long_desc": null,
                    "hint": [],
                    "tags": [],
                    "modifiers": "",
                    "default": null,
                    "is_by_ref": false
                }
            }
        },
        "upload": {
            "name": "upload",
            "line": 66,
            "short_desc": "",
            "long_desc": "",
            "hint": [
                [
                    "\\Tavro\\Bundle\\CoreBundle\\Model\\EntityInterface",
                    false
                ],
                [
                    "mixed",
                    false
                ],
                [
                    "\\Symfony\\Component\\HttpFoundation\\File\\UploadedFile",
                    false
                ]
            ],
            "hint_desc": "",
            "tags": [],
            "modifiers": "1",
            "is_by_ref": "",
            "exceptions": [
                [
                    "\\Exception",
                    ""
                ]
            ],
            "errors": [],
            "parameters": {
                "file": {
                    "name": "file",
                    "line": 66,
                    "short_desc": "",
                    "long_desc": null,
                    "hint": [
                        [
                            "Tavro\\Bundle\\ApiBundle\\Handler\\Symfony\\Component\\HttpFoundation\\File\\UploadedFile",
                            false
                        ]
                    ],
                    "tags": [],
                    "modifiers": "Symfony\\Component\\HttpFoundation\\File\\UploadedFile",
                    "default": null,
                    "is_by_ref": false
                },
                "directory": {
                    "name": "directory",
                    "line": 66,
                    "short_desc": "",
                    "long_desc": null,
                    "hint": [
                        [
                            "string",
                            false
                        ]
                    ],
                    "tags": [],
                    "modifiers": "",
                    "default": "''",
                    "is_by_ref": false
                }
            }
        },
        "move": {
            "name": "move",
            "line": 102,
            "short_desc": "",
            "long_desc": "",
            "hint": [
                [
                    "\\Tavro\\Bundle\\CoreBundle\\Model\\EntityInterface",
                    false
                ],
                [
                    "mixed",
                    false
                ]
            ],
            "hint_desc": "",
            "tags": [],
            "modifiers": "1",
            "is_by_ref": "",
            "exceptions": [
                [
                    "\\Exception",
                    ""
                ]
            ],
            "errors": [],
            "parameters": {
                "data": {
                    "name": "data",
                    "line": 102,
                    "short_desc": "",
                    "long_desc": null,
                    "hint": [
                        [
                            "array",
                            false
                        ]
                    ],
                    "tags": [],
                    "modifiers": "array",
                    "default": null,
                    "is_by_ref": false
                },
                "filename": {
                    "name": "filename",
                    "line": 102,
                    "short_desc": "",
                    "long_desc": null,
                    "hint": [],
                    "tags": [],
                    "modifiers": "",
                    "default": null,
                    "is_by_ref": false
                },
                "directory": {
                    "name": "directory",
                    "line": 102,
                    "short_desc": "",
                    "long_desc": null,
                    "hint": [
                        [
                            "string",
                            false
                        ]
                    ],
                    "tags": [],
                    "modifiers": "",
                    "default": "''",
                    "is_by_ref": false
                }
            }
        },
        "delete": {
            "name": "delete",
            "line": 151,
            "short_desc": "",
            "long_desc": "",
            "hint": [
                [
                    "\\Tavro\\Bundle\\CoreBundle\\Model\\EntityInterface",
                    false
                ]
            ],
            "hint_desc": "",
            "tags": [],
            "modifiers": "1",
            "is_by_ref": "",
            "exceptions": [],
            "errors": [],
            "parameters": {
                "entity": {
                    "name": "entity",
                    "line": 151,
                    "short_desc": "",
                    "long_desc": null,
                    "hint": [
                        [
                            "Tavro\\Bundle\\ApiBundle\\Model\\Tavro\\Bundle\\CoreBundle\\Model\\EntityInterface",
                            false
                        ]
                    ],
                    "tags": [],
                    "modifiers": "Tavro\\Bundle\\CoreBundle\\Model\\EntityInterface",
                    "default": null,
                    "is_by_ref": false
                }
            }
        }
    },
    "constants": []
}